runthis/__init__.py
runthis/conventions.py
runthis-0.0.3.dist-info/LICENSE
runthis-0.0.3.dist-info/METADATA
runthis-0.0.3.dist-info/WHEEL
runthis-0.0.3.dist-info/entry_points.txt
runthis-0.0.3.dist-info/top_level.txt
runthis-0.0.3.dist-info/RECORD
