Metadata-Version: 2.1
Name: runthis
Version: 0.0.3
Summary: Micro-utility for staying organized running experiments
Home-page: https://github.com/microprediction/runthis
Author: microprediction
Author-email: peter.cotton@microprediction.com
License: MIT
Platform: UNKNOWN
Classifier: License :: OSI Approved :: MIT License
Classifier: Programming Language :: Python :: 3
Classifier: Programming Language :: Python :: 3.7
Classifier: Programming Language :: Python :: 3.8
License-File: LICENSE
Requires-Dist: wheel
Requires-Dist: pathlib
